Workbook

Sheet Read Me
A2: YIELD HEALTHCARE — TECHNOLOGY START-UP COSTS
B4: This workbook estimates the one-time and recurring technology costs to stand up Yield Healthcare as a company: acquiring the yieldhealthcare.com domain, business email and Microsoft 365, a HIPAA-compliant phone system, and the cloud infrastructure and tooling needed to build and host the platform.
B6: Tabs:
B7: Assumptions — seat counts, vendor selections, and pricing inputs behind every line item. Blue text = editable input.
B8: Cost Detail — every line item with one-time cost, monthly cost, and annualized cost, grouped by category.
B9: Summary — rollup by category, Year 1 total, and a cost-mix chart.
B11: Scope note: this workbook covers technology infrastructure and tooling only — domain, email, phone, hosting, and dev/compliance tooling. Engineering and clinical operations headcount costs are tracked separately in the Org & Capital section of the TEAM and PMPM business cases, not duplicated here.
B13: How to use it: change any blue cell on the Assumptions tab and the Cost Detail and Summary tabs recalculate.
B15: Sourced figures (verified July 2026): GoDaddy Domain Broker Service fee ($119.99 upfront, non-refundable, plus 20% commission on final sale price, godaddy.com/domains/domain-broker). GoDaddy Microsoft 365 Online Business Essentials pricing ($7.99/user/mo introductory, $14.99/user/mo renewal). PanTerra Networks base plan pricing ($17.95/user/mo, native HIPAA/HITECH compliance included at no extra cost). RingCentral RingEX Core pricing ($20/user/mo annual billing; BAA available on request) shown for comparison. HIPAA-compliant cloud hosting range ($300–$5,000+/mo depending on scale, per multiple 2026 HIPAA hosting cost surveys). Drata SOC 2/HIPAA compliance automation entry pricing (from $3,000/yr). The anticipated yieldhealthcare.com purchase price is a planning estimate based on 2025 secondary-market pricing for two-word brandable .com domains (typically $500–$5,000+), not a quote from the domain's current owner — actual price is subject to the 30-day broker negotiation.

Sheet Assumptions
A1: ASSUMPTIONS
A3: 1. Team Size
A4: Input | B4: Value
A5: Founding team seats (Year 1) | B5: 8
A6: Lean founding team per the TEAM business case: clinical operations lead, data/analytics lead, compliance lead, small enterprise sales function, plus early technical hires. Drives email, Microsoft 365, and phone seat counts below.
A8: 2. Domain — yieldhealthcare.com
A9: Input | B9: Value
A10: GoDaddy Domain Broker Service fee (upfront, non-refundable) | B10: 119.99
A11: Anticipated domain purchase price (planning estimate) | B11: 5000
A12: GoDaddy broker commission rate (% of purchase price) | B12: 0.2
A13: Standard .com annual renewal (after acquisition) | B13: 20
A14: Purchase price is a planning estimate, not a quote — two-word brandable .com domains typically resell for $500–$5,000+ depending on the seller. Actual price is set through GoDaddy's 30-day broker negotiation and could land above or below this estimate.
A16: 3. Email & Microsoft 365 (via GoDaddy)
A17: Input | B17: Value
A18: Plan: Microsoft 365 Online Business Essentials
A19: Price per user/month — Year 1 introductory rate | B19: 7.99
A20: Price per user/month — renewal rate (Year 2+) | B20: 14.99
A21: Business Essentials tier includes full Microsoft 365 apps (Word, Excel, PowerPoint, Teams) plus hosted email, not just email-only hosting.
A23: 4. Phone System — PanTerra Networks (HIPAA-compliant)
A24: Input | B24: Value
A25: Price per user/month (base plan) | B25: 17.95
A26: Selected as the cheapest HIPAA/HITECH-compliant option evaluated: HIPAA compliance is native to every PanTerra plan at no added cost. RingCentral RingEX Core runs $20/user/mo (annual billing) and requires requesting a separate BAA for HIPAA use — shown on the Cost Detail tab for comparison, not selected.
A28: 5. Platform Infrastructure
A29: Input | B29: Value
A30: HIPAA-compliant cloud hosting (AWS/Azure, signed BAA) — monthly | B30: 750
A31: Dev / staging (non-production) environment — monthly | B31: 250
A32: Source control & project management tooling — monthly | B32: 100
A33: HIPAA/SOC 2 compliance automation platform — annual | B33: 3000
A34: Security monitoring, backup & SSL — monthly | B34: 75
A35: Hosting cost is a Year 1 average — HIPAA-compliant hosting runs $300–$5,000+/mo depending on scale; $750/mo assumes an early-stage MVP ramping over the year. Compliance platform entry tier (e.g., Drata) starts near $3,000/yr; a full external SOC 2 Type II audit ($10,000–$50,000) is treated as a Year 2 milestone once the platform has operating history, and is called out but not included in the Year 1 total below.
A37: Row references used by the Cost Detail tab — do not delete rows above without checking Cost Detail formulas.

Sheet Cost Detail
A1: TECHNOLOGY START-UP COST DETAIL
A3: Category | B3: Item | C3: One-Time Cost | D3: Monthly Cost | E3: Annualized Cost (Yr 1)
A4: Domain | B4: GoDaddy Domain Broker Service fee (upfront) | C4: =Assumptions!B10 -> 119.99 | D4: 0 | E4: 0
A5: Domain | B5: Anticipated yieldhealthcare.com purchase price | C5: =Assumptions!B11 -> 5000 | D5: 0 | E5: 0
A6: Domain | B6: GoDaddy broker commission (20% of purchase price) | C6: =Assumptions!B11*Assumptions!B12 -> 1000 | D6: 0 | E6: 0
A7: Domain | B7: Standard .com annual renewal | C7: 0 | D7: 0 | E7: =Assumptions!B13 -> 20
A8: Email / Microsoft 365 | B8: Microsoft 365 Business Essentials, founding team seats, Yr 1 intro rate | C8: 0 | D8: =Assumptions!B5*Assumptions!B19 -> 63.92 | E8: =D8*12 -> 767.04
A9: Phone System | B9: PanTerra Networks (HIPAA-compliant), selected | C9: 0 | D9: =Assumptions!B5*Assumptions!B25 -> 143.6 | E9: =D9*12 -> 1723.2
A10: Platform Infrastructure | B10: HIPAA-compliant cloud hosting (AWS/Azure, BAA) | C10: 0 | D10: =Assumptions!B30 -> 750 | E10: =D10*12 -> 9000
A11: Platform Infrastructure | B11: Dev / staging environment | C11: 0 | D11: =Assumptions!B31 -> 250 | E11: =D11*12 -> 3000
A12: Platform Infrastructure | B12: Source control & project management tooling | C12: 0 | D12: =Assumptions!B32 -> 100 | E12: =D12*12 -> 1200
A13: Platform Infrastructure | B13: HIPAA / SOC 2 compliance automation platform | C13: 0 | D13: =Assumptions!B33/12 -> 250 | E13: =Assumptions!B33 -> 3000
A14: Platform Infrastructure | B14: Security monitoring, backup & SSL | C14: 0 | D14: =Assumptions!B34 -> 75 | E14: =D14*12 -> 900
B16: YEAR 1 TOTAL | C16: =SUM(C4:C14) -> 6119.99 | D16: =SUM(D4:D14) -> 1632.52 | E16: =SUM(E4:E14) -> 19610.24
B17: Grand total (one-time + Year 1 annualized recurring) | E17: =C16+E16 -> 25730.23
A19: Alternative considered — not selected
A21: Category | B21: Item | C21: One-Time Cost | D21: Monthly Cost | E21: Annualized Cost
A22: Phone System (alt.) | B22: RingCentral RingEX Core, annual billing — requires separate BAA request for HIPAA use | C22: 0 | D22: =Assumptions!B5*20 -> 160 | E22: =D22*12 -> 1920
A23: Shown for comparison only; excluded from the Year 1 total above. PanTerra was selected because HIPAA/HITECH compliance is native to its base plan at no added cost, while RingCentral requires requesting a BAA separately and its comparable HIPAA-ready tier runs at or above this Core prod pricing.

Sheet Summary
A1: YEAR 1 TECHNOLOGY COST SUMMARY
A3: Category | B3: Year 1 Cost
A4: Domain | B4: =SUMIF('Cost Detail'!$A$4:$A$14,A4,'Cost Detail'!$C$4:$C$14)+SUMIF('Cost Detail'!$A$4:$A$14,A4,'Cost Detail'!$E$4:$E$14) -> 6139.99
A5: Email / Microsoft 365 | B5: =SUMIF('Cost Detail'!$A$4:$A$14,A5,'Cost Detail'!$C$4:$C$14)+SUMIF('Cost Detail'!$A$4:$A$14,A5,'Cost Detail'!$E$4:$E$14) -> 767.04
A6: Phone System | B6: =SUMIF('Cost Detail'!$A$4:$A$14,A6,'Cost Detail'!$C$4:$C$14)+SUMIF('Cost Detail'!$A$4:$A$14,A6,'Cost Detail'!$E$4:$E$14) -> 1723.2
A7: Platform Infrastructure | B7: =SUMIF('Cost Detail'!$A$4:$A$14,A7,'Cost Detail'!$C$4:$C$14)+SUMIF('Cost Detail'!$A$4:$A$14,A7,'Cost Detail'!$E$4:$E$14) -> 17100
A8: GRAND TOTAL — YEAR 1 | B8: =SUM(B4:B7) -> 25730.23
A10: "Year 1 Cost" = one-time costs (domain broker fee, purchase price, commission) plus twelve months of every recurring line item — the total cash a new company should plan to have available for technology in its first year, before engineering/clinical headcount.
A13: Cost Mix by Category
A14: Category | B14: Year 1 Cost | C14: % of Total | D14: Cost Mix
A15: Domain | B15: =B4 -> 6139.99 | C15: =B4/$B$8 -> 0.23862943 | D15: =REPT("█",ROUND(C15*40,0)) -> ██████████
A16: Email / Microsoft 365 | B16: =B5 -> 767.04 | C16: =B5/$B$8 -> 0.029810849 | D16: =REPT("█",ROUND(C16*40,0)) -> █
A17: Phone System | B17: =B6 -> 1723.2 | C17: =B6/$B$8 -> 0.066971807 | D17: =REPT("█",ROUND(C17*40,0)) -> ███
A18: Platform Infrastructure | B18: =B7 -> 17100 | C18: =B7/$B$8 -> 0.66458792 | D18: =REPT("█",ROUND(C18*40,0)) -> ███████████████████████████
